{
  "project_info": {
    "project_number": "932925773468",
    "firebase_url": "https://helpshop-2945c.firebaseio.com",
    "project_id": "helpshop-2945c",
    "storage_bucket": "helpshop-2945c.appspot.com"
  },
  "client": [
    {
      "client_info": {
        "mobilesdk_app_id": "1:932925773468:android:5bea399a0902ae9799ff59",
        "android_client_info": {
          "package_name": "com.example.hackovid"
        }
      },
      "oauth_client": [
        {
          "client_id": "932925773468-6e2t2q8srr97h0lu1a4j2s4jo3u3b12q.apps.googleusercontent.com",
          "client_type": 3
        }
      ],
      "api_key": [
        {
          "current_key": "AIzaSyDWhHHKyUGS33W048pMiXH_g-JUmrZ6P_g"
        }
      ],
      "services": {
        "appinvite_service": {
          "other_platform_oauth_client": [
            {
              "client_id": "932925773468-6e2t2q8srr97h0lu1a4j2s4jo3u3b12q.apps.googleusercontent.com",
              "client_type": 3
            }
          ]
        }
      }
    }
  ],
  "configuration_version": "1"
}